README.rst
setup.py
scrapy_grpc/__init__.py
scrapy_grpc/client.py
scrapy_grpc/webservice.py
scrapy_grpc.egg-info/PKG-INFO
scrapy_grpc.egg-info/SOURCES.txt
scrapy_grpc.egg-info/dependency_links.txt
scrapy_grpc.egg-info/not-zip-safe
scrapy_grpc.egg-info/requires.txt
scrapy_grpc.egg-info/top_level.txt