Metadata-Version: 1.1
Name: scrapy-grpc
Version: 1.0
Summary: Scrapy extension to control spiders using gRPC
Home-page: https://github.com/rangertaha/scrapy-grpc
Author: rangertaha
Author-email: UNKNOWN
License: MIT
Platform: UNKNOWN
Classifier: Framework :: Scrapy
Classifier: Development Status :: 4 - Beta
Classifier: Environment :: Console
Classifier: Intended Audience :: Developers
Classifier: License :: OSI Approved :: BSD License
Classifier: Operating System :: OS Independent
Classifier: Programming Language :: Python
Classifier: Programming Language :: Python :: 2
Classifier: Programming Language :: Python :: 2.7
Classifier: Topic :: Internet :: WWW/HTTP
